xinetzone/__init__.py
xinetzone/themes/xinetzone/layout.html
xinetzone/themes/xinetzone/theme.conf
xinetzone/themes/xinetzone/_templates/copyright.html
xinetzone/themes/xinetzone/_templates/edit-this-page.html
xinetzone/themes/xinetzone/_templates/last-updated.html
xinetzone/themes/xinetzone/_templates/navbar-icon-links.html
xinetzone/themes/xinetzone/_templates/navbar-logo.html
xinetzone/themes/xinetzone/_templates/navbar-nav.html
xinetzone/themes/xinetzone/_templates/page-toc.html
xinetzone/themes/xinetzone/_templates/prev-next.html
xinetzone/themes/xinetzone/_templates/sidebar-ethical-ads.html
xinetzone/themes/xinetzone/_templates/sidebar-nav-bs.html
xinetzone/themes/xinetzone/_templates/sphinx-version.html
xinetzone/themes/xinetzone/_templates/theme-switcher.html
xinetzone/themes/xinetzone/_templates/version-switcher.html
xinetzone/themes/xinetzone/static/css/custom.css
xinetzone/themes/xinetzone/static/css/default.css
xinetzone-0.0.1.dist-info/entry_points.txt
xinetzone-0.0.1.dist-info/LICENSE
xinetzone-0.0.1.dist-info/WHEEL
xinetzone-0.0.1.dist-info/METADATA
xinetzone-0.0.1.dist-info/RECORD
